healpix_geo/__init__.py
healpix_geo/geometry.py
healpix_geo/healpix_geo.cpython-313-arm-linux-gnueabihf.so
healpix_geo/nested.py
healpix_geo/ring.py
healpix_geo/slices.py
healpix_geo/tests/test_conversion.py
healpix_geo/tests/test_coverage.py
healpix_geo/tests/test_distances.py
healpix_geo/tests/test_index.py
healpix_geo/tests/test_inference.py
healpix_geo/tests/test_neighbours.py
healpix_geo/tests/test_slices.py
healpix_geo/tests/test_zoom.py
healpix_geo/utils.py
healpix_geo/zuniq.py
healpix_geo-0.0.9.dist-info/METADATA
healpix_geo-0.0.9.dist-info/WHEEL
healpix_geo-0.0.9.dist-info/licenses/LICENSE
healpix_geo-0.0.9.dist-info/RECORD
