Metadata-Version: 2.4
Name: healpix-geo
Version: 0.0.9
Classifier: Programming Language :: Rust
Classifier: Programming Language :: Python :: Implementation :: CPython
Requires-Dist: numpy
Requires-Dist: shapely>=2 ; extra == 'geometries'
Provides-Extra: geometries
License-File: LICENSE
License-Expression: Apache-2.0
Requires-Python: >=3.10
